<annotation>
	<folder></folder>
	<filename>frame174_jpg.rf.fd444f6a96741df8f4774bc8b5be5f8f.jpg</filename>
	<path>frame174_jpg.rf.fd444f6a96741df8f4774bc8b5be5f8f.jpg</path>
	<source>
		<database>roboflow.ai</database>
	</source>
	<size>
		<width>352</width>
		<height>352</height>
		<depth>3</depth>
	</size>
	<segmented>0</segmented>
	<object>
		<name>0</name>
		<pose>Unspecified</pose>
		<truncated>0</truncated>
		<difficult>0</difficult>
		<occluded>0</occluded>
		<bndbox>
			<xmin>2</xmin>
			<xmax>43</xmax>
			<ymin>46</ymin>
			<ymax>191</ymax>
		</bndbox>
	</object>
	<object>
		<name>0</name>
		<pose>Unspecified</pose>
		<truncated>0</truncated>
		<difficult>0</difficult>
		<occluded>0</occluded>
		<bndbox>
			<xmin>90</xmin>
			<xmax>300</xmax>
			<ymin>15</ymin>
			<ymax>106</ymax>
		</bndbox>
	</object>
	<object>
		<name>0</name>
		<pose>Unspecified</pose>
		<truncated>0</truncated>
		<difficult>0</difficult>
		<occluded>0</occluded>
		<bndbox>
			<xmin>132</xmin>
			<xmax>248</xmax>
			<ymin>109</ymin>
			<ymax>199</ymax>
		</bndbox>
	</object>
	<object>
		<name>0</name>
		<pose>Unspecified</pose>
		<truncated>0</truncated>
		<difficult>0</difficult>
		<occluded>0</occluded>
		<bndbox>
			<xmin>251</xmin>
			<xmax>352</xmax>
			<ymin>114</ymin>
			<ymax>289</ymax>
		</bndbox>
	</object>
	<object>
		<name>0</name>
		<pose>Unspecified</pose>
		<truncated>0</truncated>
		<difficult>0</difficult>
		<occluded>0</occluded>
		<bndbox>
			<xmin>232</xmin>
			<xmax>258</xmax>
			<ymin>257</ymin>
			<ymax>320</ymax>
		</bndbox>
	</object>
	<object>
		<name>0</name>
		<pose>Unspecified</pose>
		<truncated>0</truncated>
		<difficult>0</difficult>
		<occluded>0</occluded>
		<bndbox>
			<xmin>57</xmin>
			<xmax>89</xmax>
			<ymin>171</ymin>
			<ymax>201</ymax>
		</bndbox>
	</object>
</annotation>
