<annotation>
	<folder></folder>
	<filename>frame270_jpg.rf.a809fc2e1d2f62c449c99eec1dc00dc5.jpg</filename>
	<path>frame270_jpg.rf.a809fc2e1d2f62c449c99eec1dc00dc5.jpg</path>
	<source>
		<database>roboflow.ai</database>
	</source>
	<size>
		<width>352</width>
		<height>352</height>
		<depth>3</depth>
	</size>
	<segmented>0</segmented>
	<object>
		<name>0</name>
		<pose>Unspecified</pose>
		<truncated>0</truncated>
		<difficult>0</difficult>
		<occluded>0</occluded>
		<bndbox>
			<xmin>94</xmin>
			<xmax>122</xmax>
			<ymin>135</ymin>
			<ymax>260</ymax>
		</bndbox>
	</object>
	<object>
		<name>0</name>
		<pose>Unspecified</pose>
		<truncated>0</truncated>
		<difficult>0</difficult>
		<occluded>0</occluded>
		<bndbox>
			<xmin>126</xmin>
			<xmax>157</xmax>
			<ymin>104</ymin>
			<ymax>260</ymax>
		</bndbox>
	</object>
	<object>
		<name>0</name>
		<pose>Unspecified</pose>
		<truncated>0</truncated>
		<difficult>0</difficult>
		<occluded>0</occluded>
		<bndbox>
			<xmin>202</xmin>
			<xmax>217</xmax>
			<ymin>197</ymin>
			<ymax>232</ymax>
		</bndbox>
	</object>
	<object>
		<name>0</name>
		<pose>Unspecified</pose>
		<truncated>0</truncated>
		<difficult>0</difficult>
		<occluded>0</occluded>
		<bndbox>
			<xmin>229</xmin>
			<xmax>256</xmax>
			<ymin>200</ymin>
			<ymax>228</ymax>
		</bndbox>
	</object>
</annotation>
